{
  "DataForNerds": {
    "LastUpdatedUTC": "2024-10-01T17:14:32.1496102Z",
    "SourceList": [
      "https://learn.microsoft.com/en-us/lifecycle/products/windows-10-enterprise-and-education",
      "https://learn.microsoft.com/en-us/lifecycle/products/windows-11-enterprise-and-education",
      "https://learn.microsoft.com/en-us/lifecycle/products/windows-10-home-and-pro",
      "https://learn.microsoft.com/en-us/lifecycle/products/windows-11-home-and-pro"
    ]
  },
  "Data": [
    {
      "Version": "1507",
      "SKU": "Windows 10 Home and Pro",
      "StartDate": "2015-07-29",
      "EndDate": "2017-05-10"
    },
    {
      "Version": "1507",
      "SKU": "Windows 10 Enterprise and Education",
      "StartDate": "2015-07-29",
      "EndDate": "2017-05-10"
    },
    {
      "Version": "1511",
      "SKU": "Windows 10 Enterprise and Education",
      "StartDate": "2015-11-10",
      "EndDate": "2017-10-11"
    },
    {
      "Version": "1511",
      "SKU": "Windows 10 Home and Pro",
      "StartDate": "2015-11-10",
      "EndDate": "2017-10-11"
    },
    {
      "Version": "1607",
      "SKU": "Windows 10 Home and Pro",
      "StartDate": "2016-08-02",
      "EndDate": "2018-04-11"
    },
    {
      "Version": "1607",
      "SKU": "Windows 10 Enterprise and Education",
      "StartDate": "2016-08-02",
      "EndDate": "2019-04-10"
    },
    {
      "Version": "1703",
      "SKU": "Windows 10 Home and Pro",
      "StartDate": "2017-04-11",
      "EndDate": "2018-10-10"
    },
    {
      "Version": "1703",
      "SKU": "Windows 10 Enterprise and Education",
      "StartDate": "2017-04-11",
      "EndDate": "2019-10-09"
    },
    {
      "Version": "1709",
      "SKU": "Windows 10 Home and Pro",
      "StartDate": "2017-10-17",
      "EndDate": "2019-04-10"
    },
    {
      "Version": "1709",
      "SKU": "Windows 10 Enterprise and Education",
      "StartDate": "2017-10-17",
      "EndDate": "2020-10-14"
    },
    {
      "Version": "1803",
      "SKU": "Windows 10 Home and Pro",
      "StartDate": "2018-04-30",
      "EndDate": "2019-11-13"
    },
    {
      "Version": "1803",
      "SKU": "Windows 10 Enterprise and Education",
      "StartDate": "2018-04-30",
      "EndDate": "2021-05-12"
    },
    {
      "Version": "1809",
      "SKU": "Windows 10 Home and Pro",
      "StartDate": "2018-11-13",
      "EndDate": "2020-11-11"
    },
    {
      "Version": "1809",
      "SKU": "Windows 10 Enterprise and Education",
      "StartDate": "2018-11-13",
      "EndDate": "2021-05-12"
    },
    {
      "Version": "1903",
      "SKU": "Windows 10 Home and Pro",
      "StartDate": "2019-05-21",
      "EndDate": "2020-12-09"
    },
    {
      "Version": "1903",
      "SKU": "Windows 10 Enterprise and Education",
      "StartDate": "2019-05-21",
      "EndDate": "2020-12-09"
    },
    {
      "Version": "1909",
      "SKU": "Windows 10 Enterprise and Education",
      "StartDate": "2019-11-12",
      "EndDate": "2022-05-11"
    },
    {
      "Version": "1909",
      "SKU": "Windows 10 Home and Pro",
      "StartDate": "2019-11-12",
      "EndDate": "2021-05-12"
    },
    {
      "Version": "2004",
      "SKU": "Windows 10 Enterprise and Education",
      "StartDate": "2020-05-27",
      "EndDate": "2021-12-15"
    },
    {
      "Version": "2004",
      "SKU": "Windows 10 Home and Pro",
      "StartDate": "2020-05-27",
      "EndDate": "2021-12-15"
    },
    {
      "Version": "20H2",
      "SKU": "Windows 10 Enterprise and Education",
      "StartDate": "2020-10-20",
      "EndDate": "2023-05-10"
    },
    {
      "Version": "20H2",
      "SKU": "Windows 10 Home and Pro",
      "StartDate": "2020-10-20",
      "EndDate": "2022-05-11"
    },
    {
      "Version": "21H1",
      "SKU": "Windows 10 Enterprise and Education",
      "StartDate": "2021-05-18",
      "EndDate": "2022-12-14"
    },
    {
      "Version": "21H1",
      "SKU": "Windows 10 Home and Pro",
      "StartDate": "2021-05-18",
      "EndDate": "2022-12-14"
    },
    {
      "Version": "21H2",
      "SKU": "Windows 11 Enterprise and Education",
      "StartDate": "2021-10-04",
      "EndDate": "2024-10-09"
    },
    {
      "Version": "21H2",
      "SKU": "Windows 11 Home and Pro",
      "StartDate": "2021-10-04",
      "EndDate": "2023-10-11"
    },
    {
      "Version": "21H2",
      "SKU": "Windows 10 Enterprise and Education",
      "StartDate": "2021-11-16",
      "EndDate": "2024-06-12"
    },
    {
      "Version": "21H2",
      "SKU": "Windows 10 Home and Pro",
      "StartDate": "2021-11-16",
      "EndDate": "2023-06-14"
    },
    {
      "Version": "22H2",
      "SKU": "Windows 10 Home and Pro",
      "StartDate": "2022-10-18",
      "EndDate": "2025-10-15"
    },
    {
      "Version": "22H2",
      "SKU": "Windows 11 Home and Pro",
      "StartDate": "2022-09-20",
      "EndDate": "2024-10-09"
    },
    {
      "Version": "22H2",
      "SKU": "Windows 11 Enterprise and Education",
      "StartDate": "2022-09-20",
      "EndDate": "2025-10-15"
    },
    {
      "Version": "22H2",
      "SKU": "Windows 10 Enterprise and Education",
      "StartDate": "2022-10-18",
      "EndDate": "2025-10-15"
    },
    {
      "Version": "23H2",
      "SKU": "Windows 11 Enterprise and Education",
      "StartDate": "2023-10-31",
      "EndDate": "2026-11-11"
    },
    {
      "Version": "23H2",
      "SKU": "Windows 11 Home and Pro",
      "StartDate": "2023-10-31",
      "EndDate": "2025-11-12"
    },
    {
      "Version": "24H2",
      "SKU": "Windows 11 Enterprise and Education",
      "StartDate": "2024-10-01",
      "EndDate": "2027-10-13"
    },
    {
      "Version": "24H2",
      "SKU": "Windows 11 Home and Pro",
      "StartDate": "2024-10-01",
      "EndDate": "2026-10-14"
    }
  ]
}
